[
    {
        "id": 1,
        "input": {
            "event": "公司宣佈研發的新產品因技術問題延遲上市，導致股價當天暴跌15%。",
            "boss_order": "鸡肋"
        },
        "manager_output": "我認為：老板可能對目前的情況感到挫折和失望，但他也觉得新产品可能存在一些根本性的问题。\n指令：立即組織專案小組重新評估新產品的技術方案；同時加強與股東溝通，做好投資者關係管理。",
        "staff_output": "[2, 2, 1, 4, 4]"
    },
    {
        "id": 2,
        "input": {
            "event": "銷售部門本季度的收入超額完成了20%。",
            "boss_order": "繼續努力"
        },
        "manager_output": "我認為：老板對銷售部門本季度的表現表示滿意，但希望團隊能夠保持現有的努力水平。\n指令：銷售團隊請继续保持目前的積極態勢，並尋找機會進一步提高績效。行政部請準備一份本季度銷售報告，包括具體達成情況及改進建議。",
        "staff_output": "[2, 2, 1, 4, 4]"
    },
    {
        "id": 3,
        "input": {
            "event": "市場部提出了新的廣告策略，但執行成本高於預算。",
            "boss_order": "再等等看"
        },
        "manager_output": "我認為：老板可能對當前的財政狀況感到擔憂，暫時不希望投入過多資金在新廣告策略上。\n指令：市場部先優化 Advertising Strategy 的細節，尋找降低成本的方法。如果可行，再重新提交評估報告。",
        "staff_output": "[2, 3, 1, 4, 4]"
    },
    {
        "id": 4,
        "input": {
            "event": "公司的主要競爭對手最近推出了更具創新性的產品。",
            "boss_order": "隨機應變"
        },
        "manager_output": "我認為：老板希望我們能靈活應對市場上的新變化，但言簡意闢，沒有明確指示我們該如何行動。\n指令：立即分析 Competitor 的新產品特性並研究我們的產品優勢與不足。準備在下次會議中提出策略建議，以期保持競爭力。",
        "staff_output": "[2, 3, 1, 4, 1]"
    }
]